pip_licenses_cli-3.0.1.dist-info/licenses/LICENSE.txt
piplicenses/__init__.py
piplicenses/__main__.py
piplicenses/cli.py
piplicenses/collector.py
piplicenses/constants.py
piplicenses/errors.py
piplicenses/output.py
piplicenses/py.typed
piplicenses/spdx.py
pip_licenses_cli-3.0.1.dist-info/METADATA
pip_licenses_cli-3.0.1.dist-info/WHEEL
pip_licenses_cli-3.0.1.dist-info/entry_points.txt
pip_licenses_cli-3.0.1.dist-info/top_level.txt
pip_licenses_cli-3.0.1.dist-info/RECORD
