Metadata-Version: 2.4
Name: pip-licenses-cli
Version: 3.0.1
Summary: Dump the software license list of Python packages installed with pip.
Author-email: raimon <raimon49@hotmail.com>
Maintainer: stefan6419846
License-Expression: MIT
Project-URL: Homepage, https://github.com/stefan6419846/pip-licenses-cli
Project-URL: Releases, https://github.com/stefan6419846/pip-licenses-cli/releases
Project-URL: Issues, https://github.com/stefan6419846/pip-licenses-cli/issues
Keywords: pip,pypi,package,license,check
Classifier: Development Status :: 5 - Production/Stable
Classifier: Intended Audience :: Developers
Classifier: Programming Language :: Python :: 3
Classifier: Programming Language :: Python :: 3 :: Only
Classifier: Topic :: System :: Systems Administration
Classifier: Topic :: System :: System Shells
Classifier: Typing :: Typed
Requires-Python: <4,>=3.9
License-File: LICENSE.txt
Requires-Dist: pip-licenses-lib>=1.0.0
Requires-Dist: prettytable>=3.13.0
Requires-Dist: tomli>=2; python_version < "3.11"
Provides-Extra: spdx
Requires-Dist: license-expression; extra == "spdx"
Provides-Extra: dev
Requires-Dist: pip-licenses-cli[spdx]; extra == "dev"
Requires-Dist: black; extra == "dev"
Requires-Dist: coverage[toml]; extra == "dev"
Requires-Dist: cryptography>=45.0.3; extra == "dev"
Requires-Dist: docutils; extra == "dev"
Requires-Dist: flake8; extra == "dev"
Requires-Dist: flake8-bugbear; extra == "dev"
Requires-Dist: isort; extra == "dev"
Requires-Dist: mypy; extra == "dev"
Requires-Dist: pep8-naming; extra == "dev"
Requires-Dist: twine; extra == "dev"
Requires-Dist: tomli-w; extra == "dev"
Requires-Dist: types-docutils; extra == "dev"
Requires-Dist: wheel; extra == "dev"
Dynamic: license-file
